{
    "id": "10517227",
    "revid": "40901916",
    "url": "https://en.wikipedia.org/wiki?curid=10517227",
    "title": "Mount Smith",
    "text": "Mount Smith () is a &lt;a href=\"mountain\"&gt;mountain&lt;/a&gt; over 1,400\u00a0m, standing north of &lt;a href=\"Mawson%20Glacier\"&gt;Mawson Glacier&lt;/a&gt; and 7\u00a0miles (11\u00a0km) north-northwest of &lt;a href=\"Mount%20Murray%20%28Antarctica%29\"&gt;Mount Murray&lt;/a&gt; in the &lt;a href=\"Prince%20Albert%20Mountains\"&gt;Prince Albert Mountains&lt;/a&gt; in &lt;a href=\"Victoria%20Land\"&gt;Victoria Land, Antarctica&lt;/a&gt;. Discovered by the &lt;a href=\"Discovery%20Expedition\"&gt;Discovery Expedition&lt;/a&gt; (1901\u201304), which probably named this peak for W. E. Smith, Chief Naval Constructor, who prepared the plans and supervised construction of the expedition ship &lt;a href=\"RRS%20Discovery\"&gt;RRS \"Discovery\"&lt;/a&gt;."
}