{
    "id": "16866157",
    "revid": "37078343",
    "url": "https://en.wikipedia.org/wiki?curid=16866157",
    "title": "Tapinocaninus",
    "text": "Tapinocaninus is an &lt;a href=\"extinct\"&gt;extinct&lt;/a&gt; &lt;a href=\"genus\"&gt;genus&lt;/a&gt; of &lt;a href=\"therapsids\"&gt;therapsids&lt;/a&gt; in the family &lt;a href=\"Tapinocephalidae\"&gt;Tapinocephalidae&lt;/a&gt;, of which it is the most basal member. Only one species is known, \"Tapinocaninus pamelae\" (meaning \"Pam's humble canine\"). Fossils have been found dating from the &lt;a href=\"Guadalupian\"&gt;Middle Permian&lt;/a&gt; (&lt;a href=\"Wordian\"&gt;Wordian&lt;/a&gt; age).\nDescription.\nIt grew up to long, and massed up to . It is assumed to be either a herbivore or an omnivore. This dinocephalian has a heterodont dentition, consisting of incisors, canines and postcanines. It's canine teeth lack a definite crushing heel. The maxillary and premaxillary dentition is only partially preserved.\nThe species is named in honour of Rubidge's mother.\nDiscovery.\nFossils have been found in the &lt;a href=\"Eodicynodon%20Assemblage%20Zone\"&gt;Eodicynodon Assemblage Zone&lt;/a&gt; of the Karoo deposits, in the Lower Beaufort Beds in Beaufort West, by the director of the BPI, Professor Bruce Rubidge. Four specimens are known. A holotype (NMQR 2987) and three paratypes (NMQR 2985, 2986 and ROZ K95). All of them are known from skull and mandible bones."
}