{
    "id": "1786886",
    "revid": "23064323",
    "url": "https://en.wikipedia.org/wiki?curid=1786886",
    "title": "Kuntisuyu",
    "text": "Kuntisuyu or Kunti Suyu (&lt;a href=\"Quechua%20language\"&gt;Quechua&lt;/a&gt; \"kunti\" &lt;a href=\"west\"&gt;west&lt;/a&gt;, \"suyu\" region, part of a territory, each of the four regions which formed the &lt;a href=\"Inca%20Empire\"&gt;Inca Empire&lt;/a&gt;, \"western region\") was the &lt;a href=\"Ordinal%20directions\"&gt;southwestern&lt;/a&gt; provincial region of the &lt;a href=\"Inca%20Empire\"&gt;Inca Empire&lt;/a&gt;. Kuntisuyu was the smallest \"suyu\" of all and was located along the southern coast of modern Peru, extending into the highlands towards &lt;a href=\"Cusco\"&gt;Cusco&lt;/a&gt;. Along with &lt;a href=\"Qullasuyu\"&gt;Qullasuyu&lt;/a&gt;, it was part of the \"&lt;a href=\"Inca_Government%23Organization_of_the_empire\"&gt;Urin Suyukuna&lt;/a&gt;\" or \"Lower Quarters\" of the empire.\nWamani.\nEach \"suyu\" was divided into \"wamani\", or provinces. Kuntisuyu included the \"wamani\" of:"
}