{
    "id": "20234583",
    "revid": "8230836",
    "url": "https://en.wikipedia.org/wiki?curid=20234583",
    "title": "Takahiro Kawamura",
    "text": " is a former &lt;a href=\"Japan\"&gt;Japan&lt;/a&gt;ese &lt;a href=\"Association%20football\"&gt;football&lt;/a&gt; player.\nPlaying career.\nKawamura was born in &lt;a href=\"Shimada%2C%20Shizuoka\"&gt;Shimada&lt;/a&gt; on October 4, 1979. He joined &lt;a href=\"J1%20League\"&gt;J1 League&lt;/a&gt; club &lt;a href=\"J%C3%BAbilo%20Iwata\"&gt;J\u00fabilo Iwata&lt;/a&gt; from youth team in 1998. He also moved to Argentine club &lt;a href=\"Club%20Atl%C3%A9tico%20River%20Plate\"&gt;River Plate&lt;/a&gt; on loan in 1999. He played many matches as mainly defensive midfielder from 2001 and the club won the champions &lt;a href=\"2002%20J.League%20Division%201\"&gt;2002 J1 League&lt;/a&gt; and &lt;a href=\"2003%20Emperor%27s%20Cup\"&gt;2003 Emperor's Cup&lt;/a&gt;. However his opportunity to play decreased in 2005. In 2006, he moved to &lt;a href=\"Cerezo%20Osaka\"&gt;Cerezo Osaka&lt;/a&gt;. Although he played many matches, the club was relegated to &lt;a href=\"J2%20League\"&gt;J2 League&lt;/a&gt; end of 2006 season. In 2007, he moved to &lt;a href=\"Kawasaki%20Frontale\"&gt;Kawasaki Frontale&lt;/a&gt;. Although he could not play many matches, the club won the 2nd place &lt;a href=\"2007%20J.League%20Cup\"&gt;2007 J.League Cup&lt;/a&gt;. In 2008, he returned to J\u00fabilo Iwata. However he could not play many matches. In 2009, he moved to J2 club Tokyo Verdy and he played many matches. From 2010, he moved Thailand and played for &lt;a href=\"Police%20United%20F.C.\"&gt;Police United&lt;/a&gt; (2010), &lt;a href=\"TOT%20S.C.\"&gt;TOT&lt;/a&gt; (2011\u201315) and &lt;a href=\"Police%20Tero%20F.C.\"&gt;BEC Tero Sasana&lt;/a&gt; (2016). He retired end of 2016 season."
}