{
    "id": "20347847",
    "revid": "206485",
    "url": "https://en.wikipedia.org/wiki?curid=20347847",
    "title": "1962 Ohio State Buckeyes football team",
    "text": "The 1962 Ohio State Buckeyes football team represented the &lt;a href=\"Ohio%20State%20University\"&gt;Ohio State University&lt;/a&gt; in the &lt;a href=\"1962%20Big%20Ten%20Conference%20football%20season\"&gt;1962 Big Ten Conference football season&lt;/a&gt;. The Buckeyes compiled a 6\u20133 record.\nGame summaries.\nNorth Carolina.\n \n \n \nJohn Mummey 15 Rush Att, 110 Yds, 1TD; 1/1 passing, 42 yards, 1 TD\nUCLA.\n \nIllinois.\n \n \n \n \n \nNorthwestern.\n \n \nWisconsin.\n \nIowa.\n \n \n \nIndiana.\n \nOregon.\n \n \n \nMichigan.\n \n "
}