{
    "id": "20816830",
    "revid": "1062231569",
    "url": "https://en.wikipedia.org/wiki?curid=20816830",
    "title": "Shivanagi",
    "text": " Shivanagi is a village in the southern state of &lt;a href=\"Karnataka\"&gt;Karnataka&lt;/a&gt;, India. It is located in the &lt;a href=\"Bijapur%2C%20Karnataka\"&gt;Bijapur&lt;/a&gt; &lt;a href=\"taluk\"&gt;taluk&lt;/a&gt; of &lt;a href=\"Bijapur%20district%2C%20Karnataka\"&gt;Vijayapura district&lt;/a&gt; in Karnataka.\nDemographics.\n India &lt;a href=\"census\"&gt;census&lt;/a&gt;, Shivanagi had a population of 8068 with 3669 males and 3399 females."
}