{
    "id": "22916407",
    "revid": "1055869728",
    "url": "https://en.wikipedia.org/wiki?curid=22916407",
    "title": "Aleksandrs Je\u013cisejevs",
    "text": "Aleksandrs Jelisejevs (born 11 August 1971) is a retired &lt;a href=\"Latvia\"&gt;Latvia&lt;/a&gt;n international &lt;a href=\"association%20football\"&gt;football&lt;/a&gt; striker. He obtained a total number of 37 caps for the &lt;a href=\"Latvia%20national%20football%20team\"&gt;Latvia national football team&lt;/a&gt;, scoring four goals. He also played in &lt;a href=\"Finland\"&gt;Finland&lt;/a&gt;, &lt;a href=\"Hungary\"&gt;Hungary&lt;/a&gt;, &lt;a href=\"Russia\"&gt;Russia&lt;/a&gt; and &lt;a href=\"Israel\"&gt;Israel&lt;/a&gt; during his career.\nHonours.\nNational Team\nSkonto FC"
}