{
    "id": "23267021",
    "revid": "41840956",
    "url": "https://en.wikipedia.org/wiki?curid=23267021",
    "title": "Yevgeni Borisovich Yefremov",
    "text": "Yevgeni Borisovich Yefremov (; born 30 June 1970) is a Russian professional &lt;a href=\"Association%20football\"&gt;football&lt;/a&gt; coach and a former player.\nClub career.\nHe made his professional debut in the &lt;a href=\"Soviet%20Second%20League\"&gt;Soviet Second League&lt;/a&gt; in 1988 for &lt;a href=\"FC%20Torpedo%20Naberezhnye%20Chelny\"&gt;FC Torpedo Naberezhnye Chelny&lt;/a&gt;. He played six games in the &lt;a href=\"UEFA%20Intertoto%20Cup%201996\"&gt;UEFA Intertoto Cup 1996&lt;/a&gt; for &lt;a href=\"FC%20KAMAZ-Chally%20Naberezhnye%20Chelny\"&gt;FC KAMAZ-Chally Naberezhnye Chelny&lt;/a&gt;."
}