{
    "id": "2704656",
    "revid": "2808802",
    "url": "https://en.wikipedia.org/wiki?curid=2704656",
    "title": "List of newspapers in Bangladesh",
    "text": "This list of newspapers in Bangladesh is a list of &lt;a href=\"newspaper\"&gt;newspaper&lt;/a&gt;s printed and distributed in &lt;a href=\"Bangladesh\"&gt;Bangladesh&lt;/a&gt;. Newspapers published in Bangladesh are written in &lt;a href=\"Bengali%20language\"&gt;Bengali&lt;/a&gt; or English language versions. Most Bangladeshi daily newspapers are usually printed in broadsheets; few daily tabloids exist. Daily newspapers in Bangladesh are published in the capital, &lt;a href=\"Dhaka\"&gt;Dhaka&lt;/a&gt;, as well as in major regional cities such as &lt;a href=\"Chittagong\"&gt;Chittagong&lt;/a&gt;, &lt;a href=\"Khulna\"&gt;Khulna&lt;/a&gt;, &lt;a href=\"Rajshahi\"&gt;Rajshahi&lt;/a&gt;, &lt;a href=\"Sylhet\"&gt;Sylhet&lt;/a&gt; and &lt;a href=\"Barisal\"&gt;Barisal&lt;/a&gt;. All daily newspapers are morning editions; there are no evening editions in Bangladesh. Some newspapers offer online versions.\nMonthly/weekly newspapers and magazines.\nMonthly Bandhan-construction, Real estate, Interior &amp; Architecture related Popular Monthly Magazine\nNews agencies.\nBefore 1972, news agencies in Bangladesh were local branches of international &lt;a href=\"news%20agency\"&gt;agencies&lt;/a&gt;."
}