{
    "id": "27959081",
    "revid": "12406635",
    "url": "https://en.wikipedia.org/wiki?curid=27959081",
    "title": "Skew It on the Bar-B",
    "text": "\"Skew It on the Bar-B\" is the lead single released from &lt;a href=\"OutKast\"&gt;OutKast&lt;/a&gt;'s 3rd studio album, \"&lt;a href=\"Aquemini\"&gt;Aquemini&lt;/a&gt;\". The song features &lt;a href=\"Raekwon\"&gt;Raekwon&lt;/a&gt;. It failed to chart on the &lt;a href=\"Billboard%20Hot%20100\"&gt;Billboard Hot 100&lt;/a&gt;. The song features 3 verses, by &lt;a href=\"Andr%C3%A9%203000\"&gt;Andr\u00e9 3000&lt;/a&gt;, &lt;a href=\"Raekwon\"&gt;Raekwon&lt;/a&gt;, and &lt;a href=\"Big%20Boi\"&gt;Big Boi&lt;/a&gt;, in order. &lt;a href=\"Organized%20Noize\"&gt;Organized Noize&lt;/a&gt; produced the song."
}