{
    "id": "29412535",
    "revid": "3784107",
    "url": "https://en.wikipedia.org/wiki?curid=29412535",
    "title": "Virgin (2003 film)",
    "text": "Virgin is a 2003 American &lt;a href=\"drama%20film\"&gt;drama film&lt;/a&gt; directed by &lt;a href=\"Deborah%20Kampmeier\"&gt;Deborah Kampmeier&lt;/a&gt; and starring &lt;a href=\"Elisabeth%20Moss\"&gt;Elisabeth Moss&lt;/a&gt;, &lt;a href=\"Robin%20Wright%20%28actress%29\"&gt;Robin Wright&lt;/a&gt; and &lt;a href=\"Daphne%20Rubin-Vega\"&gt;Daphne Rubin-Vega&lt;/a&gt;.\nPremise.\nWhen teenage Jessie, raised very religiously, finds herself pregnant, with no memory of having had sex, she determines that she is carrying the child of God.\nAwards.\n\"Virgin\" won 5 film awards and was nominated for 3 others:"
}