{
    "id": "29722381",
    "revid": "36746161",
    "url": "https://en.wikipedia.org/wiki?curid=29722381",
    "title": "Mount Reynolds",
    "text": "Mount Reynolds () is a snow-capped &lt;a href=\"mountain\"&gt;mountain&lt;/a&gt;, 1,130 m, marked by steep, rocky lower slopes, standing at the south side of &lt;a href=\"Violante%20Inlet\"&gt;Violante Inlet&lt;/a&gt;, on the east coast of &lt;a href=\"Palmer%20Land\"&gt;Palmer Land&lt;/a&gt;. Discovered by members of the &lt;a href=\"United%20States%20Antarctic%20Service\"&gt;United States Antarctic Service&lt;/a&gt; (USAS) in a flight from &lt;a href=\"East%20Base\"&gt;East Base&lt;/a&gt; on 30 December 1940. Named by the US-SCAN for Jeremiah (John) &lt;a href=\"N.%20Reynolds\"&gt;N. Reynolds&lt;/a&gt;, longtime protagonist (1826\u201338) of American exploration and expansion in the Pacific and the Antarctic."
}