{
    "id": "30410170",
    "revid": "9784415",
    "url": "https://en.wikipedia.org/wiki?curid=30410170",
    "title": "CajaSur",
    "text": "CajaSur is a Spanish &lt;a href=\"Savings%20bank%20%28Spain%29\"&gt;savings bank&lt;/a&gt;, property of &lt;a href=\"Kutxabank\"&gt;Kutxabank&lt;/a&gt;. It has offices in &lt;a href=\"Andalusia\"&gt;Andalusia&lt;/a&gt; and &lt;a href=\"Extremadura\"&gt;Extremadura&lt;/a&gt;.\nUntil 2011, CajaSur was a Spanish &lt;a href=\"Savings%20bank%20%28Spain%29\"&gt;savings bank&lt;/a&gt;, run by the priests in the Catholic Church, located in &lt;a href=\"C%C3%B3rdoba%2C%20Spain\"&gt;C\u00f3rdoba, Spain&lt;/a&gt;. It was seized in May 2010 and defaulted in December 2010."
}