{
    "id": "30545388",
    "revid": "35936988",
    "url": "https://en.wikipedia.org/wiki?curid=30545388",
    "title": "Filip Luk\u0161\u00edk",
    "text": "Filip Luk\u0161\u00edk (born 3 February 1985) is a &lt;a href=\"Slovakia\"&gt;Slovak&lt;/a&gt; &lt;a href=\"Association%20football\"&gt;football&lt;/a&gt; defender.\nClub career.\nIn 2010, he was join to &lt;a href=\"Odra%20Wodzis%C5%82aw\"&gt;Odra Wodzis\u0142aw&lt;/a&gt; and played in polish &lt;a href=\"Ekstraklasa\"&gt;Ekstraklasa&lt;/a&gt;. On 27 June 2011, he has signed two-year contract with option for &lt;a href=\"Netherlands\"&gt;Dutch&lt;/a&gt; club &lt;a href=\"ADO%20Den%20Haag\"&gt;ADO Den Haag&lt;/a&gt; for an undisclosed fee. He was sent off in his ADO debut against &lt;a href=\"FK%20Tauras%20Taurag%C4%97\"&gt;FK Tauras&lt;/a&gt; in 1st leg of the &lt;a href=\"2011%E2%80%9312%20UEFA%20Europa%20League%20qualifying%20phase%20and%20play-off%20round%23Second%20qualifying%20round\"&gt;2011\u201312 UEFA Europa League 2nd qualifying round&lt;/a&gt; after his foul in the &lt;a href=\"penalty%20area\"&gt;penalty area&lt;/a&gt;.\nInternational career.\nLuk\u0161\u00edk made his &lt;a href=\"Slovakia%20national%20football%20team\"&gt;national team&lt;/a&gt; debut in a 1\u20130 away win against &lt;a href=\"Andorra%20national%20football%20team\"&gt;Andorra&lt;/a&gt; on 26 March 2011."
}