{
    "id": "34065320",
    "revid": "7903804",
    "url": "https://en.wikipedia.org/wiki?curid=34065320",
    "title": "Kempei Usui",
    "text": "Kempei Usui (\u7893\u4e95 \u5065\u5e73, born May 15, 1987) is a former &lt;a href=\"Japan\"&gt;Japan&lt;/a&gt;ese &lt;a href=\"Association%20football\"&gt;football&lt;/a&gt;er who last played as a &lt;a href=\"Goalkeeper%20%28association%20football%29\"&gt;goalkeeper&lt;/a&gt; for &lt;a href=\"Okinawa%20SV\"&gt;Okinawa SV&lt;/a&gt;.\nCareer.\nHis father &lt;a href=\"Hiroyuki%20Usui\"&gt;Hiroyuki&lt;/a&gt; was also a footballer, playing for the Japanese national team and the corporative version of &lt;a href=\"Kashiwa%20Reysol\"&gt;Kashiwa Reysol&lt;/a&gt; between the 1970s and 1980s. \nAfter playing for &lt;a href=\"Okinawa%20SV\"&gt;Okinawa SV&lt;/a&gt; as the last of his career, he retired in December 2019.\nClub statistics.\n\"Updated to 23 February 2020\"."
}