{
    "id": "36704162",
    "revid": "41840956",
    "url": "https://en.wikipedia.org/wiki?curid=36704162",
    "title": "Witthaya Nabthong",
    "text": "Witthaya Nabthong is a Thai &lt;a href=\"association%20football\"&gt;football&lt;/a&gt; &lt;a href=\"Defender%20%28association%20football%29\"&gt;defender&lt;/a&gt; who played for &lt;a href=\"Thailand%20national%20football%20team\"&gt;Thai internationals&lt;/a&gt; in the &lt;a href=\"2000%20AFC%20Asian%20Cup\"&gt;2000 AFC Asian Cup&lt;/a&gt;."
}