{
    "id": "36771318",
    "revid": "41639836",
    "url": "https://en.wikipedia.org/wiki?curid=36771318",
    "title": "1996 Indian Federation Cup",
    "text": "The 1996 Indian Federation Cup was the 21st season of the &lt;a href=\"Federation%20Cup%20%28India%29\"&gt;Indian Federation Cup&lt;/a&gt;. The tournament started on 29 June 1996 to 11 August. The competition was won by &lt;a href=\"East%20Bengal%20F.C.\"&gt;East Bengal&lt;/a&gt;, who defeated &lt;a href=\"Dempo%20S.C.\"&gt;Dempo&lt;/a&gt; 2\u20131 in the final."
}