{
    "id": "37085056",
    "revid": "17912182",
    "url": "https://en.wikipedia.org/wiki?curid=37085056",
    "title": "2007 Rice Owls football team",
    "text": "The 2007 Rice Owls football team represented &lt;a href=\"Rice%20University\"&gt;Rice University&lt;/a&gt; in the &lt;a href=\"2007%20NCAA%20Division%20I%20FBS%20football%20season\"&gt;2007 NCAA Division I FBS college football season&lt;/a&gt;. The Owls, led by 1st year head coach &lt;a href=\"David%20Bailiff\"&gt;David Bailiff&lt;/a&gt;, played their home games at &lt;a href=\"Rice%20Stadium%20%28Rice%20University%29\"&gt;Rice Stadium&lt;/a&gt; in &lt;a href=\"Houston\"&gt;Houston, Texas&lt;/a&gt;. Rice finished the season 3\u20139 and 3\u20135 in &lt;a href=\"Conference%20USA\"&gt;CUSA&lt;/a&gt; play."
}