{
    "id": "40783693",
    "revid": "6935794",
    "url": "https://en.wikipedia.org/wiki?curid=40783693",
    "title": "2001 African Junior Athletics Championships",
    "text": "The 2001 &lt;a href=\"African%20Junior%20Athletics%20Championships\"&gt;African Junior Athletics Championships&lt;/a&gt; was the fifth edition of the biennial, continental &lt;a href=\"athletics%20%28sport%29\"&gt;athletics&lt;/a&gt; tournament for African athletes aged &lt;a href=\"junior%20athletics\"&gt;19 years or younger&lt;/a&gt;. It was held in &lt;a href=\"R%C3%A9duit%20%28Mauritius%29\"&gt;R\u00e9duit&lt;/a&gt;, Mauritius, from 9\u201312 July. A total of 41 events were contested, 21 by men and 20 by women."
}