{
    "id": "41253077",
    "revid": "1034879",
    "url": "https://en.wikipedia.org/wiki?curid=41253077",
    "title": "Sourou Sport de Tougan",
    "text": "Sourou Sport is a &lt;a href=\"Burkina%20Faso\"&gt;Burkinab\u00e9&lt;/a&gt; &lt;a href=\"football%20%28soccer%29\"&gt;football&lt;/a&gt; club based in &lt;a href=\"Tougan\"&gt;Tougan&lt;/a&gt;, &lt;a href=\"Burkina%20Faso\"&gt;Burkina Faso&lt;/a&gt;. The team was founded in 1954 and play in the Burkinab\u00e9 Second Division.\nStadium.\nCurrently the team plays at the 2000 capacity Stade Sangoul\u00e9-Lamizana."
}