{
    "id": "41957946",
    "revid": "96340",
    "url": "https://en.wikipedia.org/wiki?curid=41957946",
    "title": "Nea Apollonia",
    "text": "Nea Apollonia () is a village and a &lt;a href=\"Communities%20and%20Municipalities%20of%20Greece\"&gt;community&lt;/a&gt; of the &lt;a href=\"Volvi%20%28municipality%29\"&gt;Volvi municipality&lt;/a&gt;. Before the 2011 local government reform it was part of the municipality of &lt;a href=\"Apollonia%2C%20Thessaloniki\"&gt;Apollonia&lt;/a&gt;, of which it was a municipal district. The 2011 census recorded 1,851 inhabitants in the village and 1,922 inhabitants in the community. The community of Nea Apollonia covers an area of 70.855\u00a0km2.\nAdministrative division.\nThe community of Volvi consists of four separate settlements: \nThe aforementioned population figures are as of 2011."
}