{
    "id": "4275491",
    "revid": "1447259",
    "url": "https://en.wikipedia.org/wiki?curid=4275491",
    "title": "Stadio Vanni Sanna",
    "text": "Stadio Vanni Sanna (formerly known as Stadio Acquedotto) is a multi-use &lt;a href=\"stadium\"&gt;stadium&lt;/a&gt; in &lt;a href=\"Sassari\"&gt;Sassari&lt;/a&gt;, Italy. It is currently used mostly for &lt;a href=\"football%20%28soccer%29\"&gt;football&lt;/a&gt; matches and is the home ground of &lt;a href=\"Sassari%20Torres\"&gt;S.E.F. Torres 1903&lt;/a&gt; and &lt;a href=\"U.S.D.%20Latte%20Dolce\"&gt;U.S.D. Latte Dolce&lt;/a&gt;. The stadium holds 12,000."
}