{
    "id": "44553377",
    "revid": "24812038",
    "url": "https://en.wikipedia.org/wiki?curid=44553377",
    "title": "Balambat (union council)",
    "text": "Balambat is a &lt;a href=\"Union%20councils%20of%20Pakistan\"&gt;union council&lt;/a&gt; in &lt;a href=\"Lower%20Dir%20District\"&gt;Lower Dir District&lt;/a&gt;, &lt;a href=\"Khyber%20Pakhtunkhwa\"&gt;Khyber Pakhtunkhwa&lt;/a&gt;, &lt;a href=\"Pakistan\"&gt;Pakistan&lt;/a&gt;.\n&lt;a href=\"Lower%20Dir%20District\"&gt;Lower Dir District&lt;/a&gt; has 37 union councils with a population of 797,852, according to the 1998 census report. The population growth rate of the Lower Dir District was 3.42% per annum between the 1981 and 1998 censuses."
}