{
    "id": "45335967",
    "revid": "23594469",
    "url": "https://en.wikipedia.org/wiki?curid=45335967",
    "title": "St. Paul's Hill",
    "text": "St. Paul's Hill () is a &lt;a href=\"hill\"&gt;hill&lt;/a&gt; in &lt;a href=\"Malacca%20City\"&gt;Malacca City&lt;/a&gt;, &lt;a href=\"Malacca\"&gt;Malacca&lt;/a&gt;, &lt;a href=\"Malaysia\"&gt;Malaysia&lt;/a&gt;. It was originally known as the Malacca Hill during the &lt;a href=\"Malacca%20Sultanate\"&gt;Malacca Sultanate&lt;/a&gt; period and Mary's Hill during the &lt;a href=\"Portuguese%20Malacca\"&gt;Portuguese Malacca&lt;/a&gt; period."
}