{
    "id": "45623422",
    "revid": "37311077",
    "url": "https://en.wikipedia.org/wiki?curid=45623422",
    "title": "Song Seung-min",
    "text": "Song Seung-min (; born 11 January 1992) is a South Korean &lt;a href=\"Association%20football\"&gt;footballer&lt;/a&gt; who plays as &lt;a href=\"Forward%20%28association%20football%29%23Striker\"&gt;striker&lt;/a&gt; for &lt;a href=\"Pohang%20Steelers\"&gt;Pohang Steelers&lt;/a&gt;.\nCareer.\nHe was selected by &lt;a href=\"Gwangju%20FC\"&gt;Gwangju FC&lt;/a&gt; in the &lt;a href=\"2014%20K%20League%20Challenge\"&gt;2014 K League&lt;/a&gt; draft."
}