{
    "id": "47330617",
    "revid": "14423536",
    "url": "https://en.wikipedia.org/wiki?curid=47330617",
    "title": "Suillus acerbus",
    "text": "Suillus acerbus is a species of &lt;a href=\"bolete\"&gt;bolete&lt;/a&gt; fungus in the family &lt;a href=\"Suillaceae\"&gt;Suillaceae&lt;/a&gt;. It was first &lt;a href=\"species%20description\"&gt;described&lt;/a&gt; scientifically by American mycologists &lt;a href=\"Alexander%20H.%20Smith\"&gt;Alexander H. Smith&lt;/a&gt; and &lt;a href=\"Harry%20D.%20Thiers\"&gt;Harry D. Thiers&lt;/a&gt; in 1964."
}