{
    "id": "4951965",
    "revid": "473593",
    "url": "https://en.wikipedia.org/wiki?curid=4951965",
    "title": "Victor Palciauskas",
    "text": "Dr. Victor Palciauskas (born Vytautas Pal\u010diauskas; October 3, 1941 in &lt;a href=\"Kaunas\"&gt;Kaunas&lt;/a&gt;) is a &lt;a href=\"Lithuania\"&gt;Lithuania&lt;/a&gt;-born American chess player who holds the &lt;a href=\"chess%20title\"&gt;chess title&lt;/a&gt; of &lt;a href=\"International%20Correspondence%20Chess%20Grandmaster\"&gt;International Correspondence Chess Grandmaster&lt;/a&gt;. He was the tenth &lt;a href=\"World%20Correspondence%20Chess%20Champion\"&gt;World Correspondence Chess Champion&lt;/a&gt; (1978\u20131984).\nPalciauskas tied for second place (undefeated 5/8, +2 \u22120 =6) behind &lt;a href=\"Mikhail%20Umansky\"&gt;Mikhail Umansky&lt;/a&gt; in a \"champion of champions\" tournament, the ICCF 50 Years World Champion Jubilee. This was a special invitational correspondence tournament involving all living former ICCF World Champions."
}