{
    "id": "50413304",
    "revid": "13791031",
    "url": "https://en.wikipedia.org/wiki?curid=50413304",
    "title": "1922\u201323 Tranmere Rovers F.C. season",
    "text": "&lt;a href=\"Tranmere%20Rovers%20F.C.\"&gt;Tranmere Rovers F.C.&lt;/a&gt; played the 1922\u201323 season in the &lt;a href=\"Football%20League%20Third%20Division%20North\"&gt;Football League Third Division North&lt;/a&gt;. It was their second season of league &lt;a href=\"Association%20football\"&gt;football&lt;/a&gt;, and they finished 16th of 20. They reached the Fourth Qualifying Round of the &lt;a href=\"FA%20Cup\"&gt;FA Cup&lt;/a&gt;."
}