{
    "id": "51531887",
    "revid": "26552045",
    "url": "https://en.wikipedia.org/wiki?curid=51531887",
    "title": "Mitch Cahalane",
    "text": "Mitch Cahalane (born 5 May 1989) is an &lt;a href=\"Australian%20people\"&gt;Australian&lt;/a&gt; professional &lt;a href=\"rugby%20league\"&gt;rugby league&lt;/a&gt; footballer who most recently played as a &lt;a href=\"Rugby%20league%20positions%23Prop\"&gt;prop&lt;/a&gt; for &lt;a href=\"Halifax%20R.L.F.C.\"&gt;Halifax&lt;/a&gt; in the &lt;a href=\"Championship%20%28rugby%20league%29\"&gt;Kingstone Press Championship&lt;/a&gt;. \nCahalane has played for the &lt;a href=\"Mount%20Pritchard%20Mounties\"&gt;Mount Pritchard Mounties&lt;/a&gt; in the &lt;a href=\"Intrust%20Super%20Premiership%20NSW\"&gt;NSW Cup&lt;/a&gt; and was previously in the system of the &lt;a href=\"Penrith%20Panthers\"&gt;Penrith Panthers&lt;/a&gt;."
}