{
    "id": "52810316",
    "revid": "1276024",
    "url": "https://en.wikipedia.org/wiki?curid=52810316",
    "title": "2016\u201317 Regional One Day Cup",
    "text": "The 2016\u201317 Regional One Day Cup was a &lt;a href=\"List%20A%20cricket\"&gt;List A&lt;/a&gt; cricket tournament in &lt;a href=\"Pakistan\"&gt;Pakistan&lt;/a&gt;. The competition ran from 8 to 27 January 2017. The final was played between &lt;a href=\"Karachi%20Whites\"&gt;Karachi Whites&lt;/a&gt; and &lt;a href=\"Peshawar%20cricket%20team\"&gt;Peshawar&lt;/a&gt;, with Peshawar winning by 124 runs.\nTeams.\nThe following teams are competing:\nPoints table.\n Teams qualified for the finals"
}