{
    "id": "56277614",
    "revid": "206485",
    "url": "https://en.wikipedia.org/wiki?curid=56277614",
    "title": "1913 University of Akron football team",
    "text": "The 1913 Akron football team represented the &lt;a href=\"University%20of%20Akron\"&gt;University of Akron&lt;/a&gt;, formerly Buchtel College, in the &lt;a href=\"1913%20college%20football%20season\"&gt;1913 college football season&lt;/a&gt;. The team was led by head coach &lt;a href=\"Frank%20Haggerty\"&gt;Frank Haggerty&lt;/a&gt;, in his fourth season. Akron was outscored by their opponents by a total of 87\u2013103."
}