{
    "id": "63795272",
    "revid": "549356",
    "url": "https://en.wikipedia.org/wiki?curid=63795272",
    "title": "Samsung Galaxy J3 (2018)",
    "text": "The Samsung Galaxy J3 (2018) (also known as \"Galaxy J3 Star\", \"Galaxy J3 Aura\", \"Galaxy J3 V (2018)\" and \"Galaxy Amp Prime 3\") is an &lt;a href=\"Android%20%28operating%20system%29\"&gt;Android&lt;/a&gt; &lt;a href=\"smartphone\"&gt;smartphone&lt;/a&gt; manufactured by &lt;a href=\"Samsung%20Electronics\"&gt;Samsung Electronics&lt;/a&gt; and was released on June 8, 2018.\nSpecifications.\nHardware.\nThe Galaxy J3 (2018) is powered by an &lt;a href=\"Exynos\"&gt;Exynos&lt;/a&gt; 7570 &lt;a href=\"System%20on%20a%20chip\"&gt;SoC&lt;/a&gt; including a quad-core 1.4\u00a0GHz &lt;a href=\"ARM%20Cortex-A53\"&gt;ARM Cortex-A53&lt;/a&gt; &lt;a href=\"Central%20processing%20unit\"&gt;CPU&lt;/a&gt;, an ARM &lt;a href=\"Mali%20%28GPU%29\"&gt;Mali-T720MP2&lt;/a&gt; &lt;a href=\"Graphics%20processing%20unit\"&gt;GPU&lt;/a&gt; with 2 GB &lt;a href=\"Random%20access%20memory\"&gt;RAM&lt;/a&gt; and 16 GB of internal storage which can be upgraded up to 400 GB via &lt;a href=\"SD%20cards%23Micro-cards\"&gt;microSD card&lt;/a&gt;.\nIt has a 5.0-inch Super &lt;a href=\"AMOLED\"&gt;AMOLED&lt;/a&gt; display with a &lt;a href=\"HD%20ready\"&gt;HD ready&lt;/a&gt; resolution. The 8 &lt;a href=\"megapixel\"&gt;MP&lt;/a&gt; rear camera features f/1.9 aperture, &lt;a href=\"autofocus\"&gt;autofocus&lt;/a&gt;, &lt;a href=\"Flash%20%28photography%29\"&gt;LED flash&lt;/a&gt;, &lt;a href=\"High%20dynamic%20range\"&gt;HDR&lt;/a&gt; and &lt;a href=\"1080p\"&gt;Full HD&lt;/a&gt; video. The front camera has 5 MP with f/2.2 aperture.\nSoftware.\nThe Galaxy J3 (2018) is shipped with &lt;a href=\"Android%20%28operating%20system%29\"&gt;Android&lt;/a&gt; &lt;a href=\"Android%20Oreo\"&gt;8.0 \"Oreo\"&lt;/a&gt; and Samsung's &lt;a href=\"Samsung%20Experience\"&gt;Experience&lt;/a&gt; user interface. &lt;a href=\"Verizon%20Wireless\"&gt;Verizon&lt;/a&gt; branded J3 (2018) and J3 V (2018) can be upgraded to &lt;a href=\"Android%20Pie\"&gt;9.0 \"Pie\"&lt;/a&gt; and &lt;a href=\"One%20UI\"&gt;One UI&lt;/a&gt;."
}