{
    "id": "66092131",
    "revid": "1979668",
    "url": "https://en.wikipedia.org/wiki?curid=66092131",
    "title": "East Gongchen Bridge station",
    "text": "East Gongchen Bridge () is a &lt;a href=\"metro%20station\"&gt;metro station&lt;/a&gt; on &lt;a href=\"Line%205%20%28Hangzhou%20Metro%29\"&gt;Line 5&lt;/a&gt; of the &lt;a href=\"Hangzhou%20Metro\"&gt;Hangzhou Metro&lt;/a&gt; in China. It is located in the &lt;a href=\"Gongshu%20District\"&gt;Gongshu District&lt;/a&gt; of Hangzhou."
}