{
    "id": "66275801",
    "revid": "35936988",
    "url": "https://en.wikipedia.org/wiki?curid=66275801",
    "title": "Aldo Cubilla",
    "text": "Aldo Sebasti\u00e1n Cubilla Bogado (born 8 January 2001) is a Paraguayan-American &lt;a href=\"association%20football\"&gt;footballer&lt;/a&gt; who plays as a &lt;a href=\"Midfielder\"&gt;left midfielder&lt;/a&gt; for &lt;a href=\"Paraguayan%20Primera%20Divisi%C3%B3n\"&gt;Paraguayan Primera Divisi\u00f3n&lt;/a&gt; side &lt;a href=\"Club%20Sol%20de%20Am%C3%A9rica\"&gt;Club Sol de Am\u00e9rica&lt;/a&gt;.\nCareer.\nClub career.\nBorn in the &lt;a href=\"United%20States\"&gt;United States&lt;/a&gt;, however of Paraguayan origin, Cubilla is a product of &lt;a href=\"Club%20Sol%20de%20Am%C3%A9rica\"&gt;Sol de Am\u00e9rica&lt;/a&gt; which he joined in 2008. On 14 July 2019, Cubilla got his official debut for &lt;a href=\"Club%20Sol%20de%20Am%C3%A9rica\"&gt;Sol de Am\u00e9rica&lt;/a&gt; in the &lt;a href=\"Paraguayan%20Primera%20Divisi%C3%B3n\"&gt;Paraguayan Primera Divisi\u00f3n&lt;/a&gt; against &lt;a href=\"Club%20Nacional\"&gt;Club Nacional&lt;/a&gt;, where he was in the starting lineup. Cubilla was also in the starting lineup in the following five matches in a row. He made a total of 7 appearances for the team in the 2019 season. In the 2020 season, Cubilla played no games for the first team and was only on the bench for one game."
}