{
    "id": "66584104",
    "revid": "32425057",
    "url": "https://en.wikipedia.org/wiki?curid=66584104",
    "title": "H\u00f4tel de Villeroy (Paris, 7th arrondissement)",
    "text": "The H\u00f4tel de Villeroy is an 18th-century building in &lt;a href=\"Paris\"&gt;Paris&lt;/a&gt;, built on the initiative of Antoine Hogguer of Saint-Gall, Baron de Presles for his mistress, the actress &lt;a href=\"Charlotte%20Desmares\"&gt;Charlotte Desmares&lt;/a&gt;.\nIt is located at no 78 rue de Varenne in the &lt;a href=\"7th%20arrondissement%20of%20Paris\"&gt;7th arrondissement&lt;/a&gt; of Paris, not far from the &lt;a href=\"H%C3%B4tel%20de%20Matignon\"&gt;H\u00f4tel de Matignon&lt;/a&gt;, located on the same street. Since 1881, it has housed the &lt;a href=\"Ministry%20of%20Agriculture%20%28France%29\"&gt;French Ministry of Agriculture and Food&lt;/a&gt;.\nIts current occupant is &lt;a href=\"Julien%20Denormandie\"&gt;Julien Denormandie&lt;/a&gt;, Minister of Agriculture and Food since July 6, 2020."
}