{
    "id": "68314764",
    "revid": "1047904628",
    "url": "https://en.wikipedia.org/wiki?curid=68314764",
    "title": "Tsogt-Ochiryn Namuuntsetseg",
    "text": "Tsogt-Ochiryn Namuuntsetseg (; born 31 March 1996) is a &lt;a href=\"Mongolia\"&gt;Mongolian&lt;/a&gt; freestyle wrestler. \nShe competed at the &lt;a href=\"2019%20World%20Wrestling%20Championships%20%E2%80%93%20Women%27s%20freestyle%2050%20kg\"&gt;2019 World Wrestling Championships&lt;/a&gt;, and 2021 Asian Wrestling Olympic Qualification Tournament.\nIn 2020, she qualified for the &lt;a href=\"2020%20Summer%20Olympics\"&gt;2020 Summer Olympics&lt;/a&gt; in Tokyo, Japan. She competed in the &lt;a href=\"Wrestling%20at%20the%202020%20Summer%20Olympics%20%E2%80%93%20Women%27s%20freestyle%2050%20kg\"&gt;women's 50 kg&lt;/a&gt; event."
}