{
    "id": "69953861",
    "revid": "37195583",
    "url": "https://en.wikipedia.org/wiki?curid=69953861",
    "title": "Janis Ross",
    "text": "Janis Ross (born 7 June 1962) is an &lt;a href=\"England\"&gt;English&lt;/a&gt; &lt;a href=\"rugby%20union\"&gt;rugby union&lt;/a&gt; footballer.\nShe competed at the &lt;a href=\"1998%20Women%27s%20Rugby%20World%20Cup\"&gt;1998 Women's Rugby World Cup&lt;/a&gt;,\nShe played for &lt;a href=\"Richmond%20F.C.\"&gt;Richmond FC&lt;/a&gt;, and Saracens."
}